{
  "character": "キ",
  "unicode": "030ad",
  "strokes": [
    {
      "id": 0,
      "points": [
        {
          "x": 27,
          "y": 40.5
        },
        {
          "x": 34.25,
          "y": 40.88
        },
        {
          "x": 71.75,
          "y": 31
        },
        {
          "x": 80.75,
          "y": 30
        }
      ]
    },
    {
      "id": 1,
      "points": [
        {
          "x": 19.5,
          "y": 65.8
        },
        {
          "x": 28.96,
          "y": 65.97
        },
        {
          "x": 78.13,
          "y": 52.98
        },
        {
          "x": 89.86999999999999,
          "y": 51.629999999999995
        }
      ]
    },
    {
      "id": 2,
      "points": [
        {
          "x": 48.87,
          "y": 16.75
        },
        {
          "x": 52.75,
          "y": 22.87
        },
        {
          "x": 61,
          "y": 82.12
        },
        {
          "x": 62.38,
          "y": 93.24000000000001
        }
      ]
    }
  ]
}