{
  "character": "ス",
  "unicode": "030b9",
  "strokes": [
    {
      "id": 0,
      "points": [
        {
          "x": 30.13,
          "y": 29.38
        },
        {
          "x": 36.75,
          "y": 30.759999999999998
        },
        {
          "x": 68,
          "y": 23.38
        },
        {
          "x": 74.5,
          "y": 29.13
        },
        {
          "x": 21,
          "y": 86.38
        }
      ]
    },
    {
      "id": 1,
      "points": [
        {
          "x": 61,
          "y": 57.25
        },
        {
          "x": 89,
          "y": 85.87
        }
      ]
    }
  ]
}